pydmm6500/__init__.py
pydmm6500/dmm6500.py
pydmm6500-2025.0.5.dist-info/licenses/LICENSE
pydmm6500-2025.0.5.dist-info/METADATA
pydmm6500-2025.0.5.dist-info/WHEEL
pydmm6500-2025.0.5.dist-info/top_level.txt
pydmm6500-2025.0.5.dist-info/RECORD
