Metadata-Version: 2.4
Name: pyDMM6500
Version: 2025.0.5
Summary: A Python library for Keithley's DMM6500
Author-email: Pierre Remacle <remacle.pierre@gmail.com>
License-Expression: MIT
Project-URL: Homepage, https://github.com/remaclepi/pyDMM6500
Keywords: DMM6500,Keithley,Instrument Control,Test and Measurement
Classifier: Programming Language :: Python :: 3
Classifier: Operating System :: OS Independent
Classifier: Intended Audience :: Developers
Classifier: Topic :: Scientific/Engineering :: Instrument Drivers
Requires-Python: >=3.9
License-File: LICENSE
Dynamic: license-file
